env_automatically/__init__.py
env_automatically/extract_env.py
env_automatically-0.0.1.dist-info/LICENSE
env_automatically-0.0.1.dist-info/METADATA
env_automatically-0.0.1.dist-info/WHEEL
env_automatically-0.0.1.dist-info/entry_points.txt
env_automatically-0.0.1.dist-info/top_level.txt
env_automatically-0.0.1.dist-info/RECORD
