Metadata-Version: 2.1
Name: env-automatically
Version: 0.0.1
Summary: Tool extract environments from settings.py to .env file
Home-page: https://github.com/thiagonf/env-automatically
Author: Thiago Nogueira
Author-email: thiagonf10@gmail.com
License: UNKNOWN
Platform: UNKNOWN
Classifier: Programming Language :: Python :: 3
Classifier: License :: OSI Approved :: MIT License
Classifier: Operating System :: OS Independent
Requires-Python: >=3.6
